{"note":"This file is an internal implementation detail to speed up HTML report generation. Its format can change at any time. You might be looking for the JSON report: https://coverage.rtfd.io/cmd.html#cmd-json","format":5,"version":"7.10.5","globals":"d392466c4a96c6876e0a88c27eb7069c","files":{"z_7e382458dca8125f___init___py":{"hash":"386f7c85aba7ee710effd0445efd4df7","index":{"url":"z_7e382458dca8125f___init___py.html","file":"src/senzing/__init__.py","description":"","nums":{"precision":0,"n_files":1,"n_statements":10,"n_excluded":0,"n_missing":0,"n_branches":0,"n_partial_branches":0,"n_missing_branches":0}}},"z_7e382458dca8125f_constants_py":{"hash":"0656f7a360d5e21ae5ffe9c72e2a7781","index":{"url":"z_7e382458dca8125f_constants_py.html","file":"src/senzing/constants.py","description":"","nums":{"precision":0,"n_files":1,"n_statements":11,"n_excluded":0,"n_missing":0,"n_branches":0,"n_partial_branches":0,"n_missing_branches":0}}},"z_7e382458dca8125f_szabstractfactory_py":{"hash":"602cab6c2c1990c3aafd4965ed04018c","index":{"url":"z_7e382458dca8125f_szabstractfactory_py.html","file":"src/senzing/szabstractfactory.py","description":"","nums":{"precision":0,"n_files":1,"n_statements":23,"n_excluded":0,"n_missing":0,"n_branches":0,"n_partial_branches":0,"n_missing_branches":0}}},"z_7e382458dca8125f_szconfig_py":{"hash":"7ab9c59ce3cd8ac91f36245707f6e86b","index":{"url":"z_7e382458dca8125f_szconfig_py.html","file":"src/senzing/szconfig.py","description":"","nums":{"precision":0,"n_files":1,"n_statements":15,"n_excluded":0,"n_missing":0,"n_branches":0,"n_partial_branches":0,"n_missing_branches":0}}},"z_7e382458dca8125f_szconfigmanager_py":{"hash":"1ff0fe0c2232fe78c5ec25236a3663f6","index":{"url":"z_7e382458dca8125f_szconfigmanager_py.html","file":"src/senzing/szconfigmanager.py","description":"","nums":{"precision":0,"n_files":1,"n_statements":26,"n_excluded":0,"n_missing":0,"n_branches":0,"n_partial_branches":0,"n_missing_branches":0}}},"z_7e382458dca8125f_szdiagnostic_py":{"hash":"9e6dbacf3fd969c05e81552f6df1f949","index":{"url":"z_7e382458dca8125f_szdiagnostic_py.html","file":"src/senzing/szdiagnostic.py","description":"","nums":{"precision":0,"n_files":1,"n_statements":15,"n_excluded":0,"n_missing":0,"n_branches":0,"n_partial_branches":0,"n_missing_branches":0}}},"z_7e382458dca8125f_szengine_py":{"hash":"935d2d2112207422834575b0260b2928","index":{"url":"z_7e382458dca8125f_szengine_py.html","file":"src/senzing/szengine.py","description":"","nums":{"precision":0,"n_files":1,"n_statements":71,"n_excluded":0,"n_missing":0,"n_branches":0,"n_partial_branches":0,"n_missing_branches":0}}},"z_7e382458dca8125f_szengineflags_py":{"hash":"4c349b9c85668d1180e9cb46d4d189de","index":{"url":"z_7e382458dca8125f_szengineflags_py.html","file":"src/senzing/szengineflags.py","description":"","nums":{"precision":0,"n_files":1,"n_statements":84,"n_excluded":0,"n_missing":1,"n_branches":0,"n_partial_branches":0,"n_missing_branches":0}}},"z_7e382458dca8125f_szerror_py":{"hash":"5f88a5464f26e41eb32cf7670d4fa042","index":{"url":"z_7e382458dca8125f_szerror_py.html","file":"src/senzing/szerror.py","description":"","nums":{"precision":0,"n_files":1,"n_statements":20,"n_excluded":0,"n_missing":0,"n_branches":0,"n_partial_branches":0,"n_missing_branches":0}}},"z_7e382458dca8125f_szhelpers_py":{"hash":"e38f887bdb8bfb63b81584ab0c6d0a2d","index":{"url":"z_7e382458dca8125f_szhelpers_py.html","file":"src/senzing/szhelpers.py","description":"","nums":{"precision":0,"n_files":1,"n_statements":24,"n_excluded":0,"n_missing":0,"n_branches":0,"n_partial_branches":0,"n_missing_branches":0}}},"z_7e382458dca8125f_szproduct_py":{"hash":"00bee5bcae8808fa06fb5eb2902cb44e","index":{"url":"z_7e382458dca8125f_szproduct_py.html","file":"src/senzing/szproduct.py","description":"","nums":{"precision":0,"n_files":1,"n_statements":11,"n_excluded":0,"n_missing":0,"n_branches":0,"n_partial_branches":0,"n_missing_branches":0}}},"z_a03a5e41ea04a006___init___py":{"hash":"a9846b2605711abc086a2bf84db1973e","index":{"url":"z_a03a5e41ea04a006___init___py.html","file":"src/senzing_mock/__init__.py","description":"","nums":{"precision":0,"n_files":1,"n_statements":2,"n_excluded":0,"n_missing":0,"n_branches":0,"n_partial_branches":0,"n_missing_branches":0}}},"z_a03a5e41ea04a006_senzing_mock_py":{"hash":"9182019f15eec91fb0955c65aaf8306f","index":{"url":"z_a03a5e41ea04a006_senzing_mock_py.html","file":"src/senzing_mock/senzing_mock.py","description":"","nums":{"precision":0,"n_files":1,"n_statements":125,"n_excluded":0,"n_missing":0,"n_branches":0,"n_partial_branches":0,"n_missing_branches":0}}},"z_1baf4de6d9c6c9ce___init___py":{"hash":"35bb38505c793f2e38a3b93a40a33ba4","index":{"url":"z_1baf4de6d9c6c9ce___init___py.html","file":"src/senzing_truthset/__init__.py","description":"","nums":{"precision":0,"n_files":1,"n_statements":5,"n_excluded":0,"n_missing":5,"n_branches":0,"n_partial_branches":0,"n_missing_branches":0}}},"z_1baf4de6d9c6c9ce_customers_py":{"hash":"4d2ef5e0363159f4db0ffe84bd9f5063","index":{"url":"z_1baf4de6d9c6c9ce_customers_py.html","file":"src/senzing_truthset/customers.py","description":"","nums":{"precision":0,"n_files":1,"n_statements":2,"n_excluded":0,"n_missing":2,"n_branches":0,"n_partial_branches":0,"n_missing_branches":0}}},"z_1baf4de6d9c6c9ce_datasources_py":{"hash":"422e4156a5217c1468139f1be9889d65","index":{"url":"z_1baf4de6d9c6c9ce_datasources_py.html","file":"src/senzing_truthset/datasources.py","description":"","nums":{"precision":0,"n_files":1,"n_statements":2,"n_excluded":0,"n_missing":2,"n_branches":0,"n_partial_branches":0,"n_missing_branches":0}}},"z_1baf4de6d9c6c9ce_references_py":{"hash":"83218ad31a5cecb8577d3c5681df6e52","index":{"url":"z_1baf4de6d9c6c9ce_references_py.html","file":"src/senzing_truthset/references.py","description":"","nums":{"precision":0,"n_files":1,"n_statements":2,"n_excluded":0,"n_missing":2,"n_branches":0,"n_partial_branches":0,"n_missing_branches":0}}},"z_1baf4de6d9c6c9ce_watchlist_py":{"hash":"d41f7ab84465ab2ebf1abd3432628728","index":{"url":"z_1baf4de6d9c6c9ce_watchlist_py.html","file":"src/senzing_truthset/watchlist.py","description":"","nums":{"precision":0,"n_files":1,"n_statements":2,"n_excluded":0,"n_missing":2,"n_branches":0,"n_partial_branches":0,"n_missing_branches":0}}}}}